[
    {
        "type": "mouse",
        "time": 0.10103082656860352,
        "event": "click",
        "button": "left",
        "pressed": false,
        "x": 353,
        "y": 159
    },
    {
        "type": "mouse",
        "time": 0.5486869812011719,
        "event": "move",
        "x": 355,
        "y": 158
    },
    {
        "type": "mouse",
        "time": 0.5566868782043457,
        "event": "move",
        "x": 355,
        "y": 158
    },
    {
        "type": "mouse",
        "time": 0.5646944046020508,
        "event": "move",
        "x": 358,
        "y": 158
    },
    {
        "type": "mouse",
        "time": 0.5726826190948486,
        "event": "move",
        "x": 361,
        "y": 158
    },
    {
        "type": "mouse",
        "time": 0.5806865692138672,
        "event": "move",
        "x": 365,
        "y": 158
    },
    {
        "type": "mouse",
        "time": 0.5886878967285156,
        "event": "move",
        "x": 370,
        "y": 158
    },
    {
        "type": "mouse",
        "time": 0.596686840057373,
        "event": "move",
        "x": 379,
        "y": 159
    },
    {
        "type": "mouse",
        "time": 0.6046867370605469,
        "event": "move",
        "x": 379,
        "y": 159
    },
    {
        "type": "mouse",
        "time": 0.6126868724822998,
        "event": "move",
        "x": 383,
        "y": 161
    },
    {
        "type": "mouse",
        "time": 0.6206824779510498,
        "event": "move",
        "x": 390,
        "y": 163
    },
    {
        "type": "mouse",
        "time": 0.6286823749542236,
        "event": "move",
        "x": 390,
        "y": 163
    },
    {
        "type": "mouse",
        "time": 0.6366822719573975,
        "event": "move",
        "x": 391,
        "y": 163
    },
    {
        "type": "mouse",
        "time": 0.6446824073791504,
        "event": "move",
        "x": 395,
        "y": 164
    },
    {
        "type": "mouse",
        "time": 0.6526820659637451,
        "event": "move",
        "x": 398,
        "y": 167
    },
    {
        "type": "mouse",
        "time": 0.6606884002685547,
        "event": "move",
        "x": 400,
        "y": 168
    },
    {
        "type": "mouse",
        "time": 0.6686837673187256,
        "event": "move",
        "x": 403,
        "y": 169
    },
    {
        "type": "mouse",
        "time": 0.6758615970611572,
        "event": "move",
        "x": 406,
        "y": 171
    },
    {
        "type": "mouse",
        "time": 0.6843698024749756,
        "event": "move",
        "x": 410,
        "y": 173
    },
    {
        "type": "mouse",
        "time": 0.6923651695251465,
        "event": "move",
        "x": 414,
        "y": 176
    },
    {
        "type": "mouse",
        "time": 0.700366735458374,
        "event": "move",
        "x": 419,
        "y": 179
    },
    {
        "type": "mouse",
        "time": 0.7083649635314941,
        "event": "move",
        "x": 424,
        "y": 183
    },
    {
        "type": "mouse",
        "time": 0.716364860534668,
        "event": "move",
        "x": 430,
        "y": 187
    },
    {
        "type": "mouse",
        "time": 0.7243654727935791,
        "event": "move",
        "x": 438,
        "y": 192
    },
    {
        "type": "mouse",
        "time": 0.7323648929595947,
        "event": "move",
        "x": 445,
        "y": 197
    },
    {
        "type": "mouse",
        "time": 0.7403647899627686,
        "event": "move",
        "x": 453,
        "y": 203
    },
    {
        "type": "mouse",
        "time": 0.7483692169189453,
        "event": "move",
        "x": 460,
        "y": 209
    },
    {
        "type": "mouse",
        "time": 0.7563650608062744,
        "event": "move",
        "x": 469,
        "y": 216
    },
    {
        "type": "mouse",
        "time": 0.7643649578094482,
        "event": "move",
        "x": 478,
        "y": 223
    },
    {
        "type": "mouse",
        "time": 0.7723655700683594,
        "event": "move",
        "x": 486,
        "y": 231
    },
    {
        "type": "mouse",
        "time": 0.7803668975830078,
        "event": "move",
        "x": 496,
        "y": 238
    },
    {
        "type": "mouse",
        "time": 0.7883694171905518,
        "event": "move",
        "x": 505,
        "y": 246
    },
    {
        "type": "mouse",
        "time": 0.7968840599060059,
        "event": "move",
        "x": 515,
        "y": 254
    },
    {
        "type": "mouse",
        "time": 0.804879903793335,
        "event": "move",
        "x": 525,
        "y": 262
    },
    {
        "type": "mouse",
        "time": 0.8128843307495117,
        "event": "move",
        "x": 535,
        "y": 269
    },
    {
        "type": "mouse",
        "time": 0.8208804130554199,
        "event": "move",
        "x": 545,
        "y": 277
    },
    {
        "type": "mouse",
        "time": 0.8288805484771729,
        "event": "move",
        "x": 569,
        "y": 296
    },
    {
        "type": "mouse",
        "time": 0.8368797302246094,
        "event": "move",
        "x": 569,
        "y": 296
    },
    {
        "type": "mouse",
        "time": 0.8448827266693115,
        "event": "move",
        "x": 581,
        "y": 306
    },
    {
        "type": "mouse",
        "time": 0.8528842926025391,
        "event": "move",
        "x": 596,
        "y": 317
    },
    {
        "type": "mouse",
        "time": 0.8608846664428711,
        "event": "move",
        "x": 611,
        "y": 329
    },
    {
        "type": "mouse",
        "time": 0.8688797950744629,
        "event": "move",
        "x": 629,
        "y": 342
    },
    {
        "type": "mouse",
        "time": 0.8768796920776367,
        "event": "move",
        "x": 648,
        "y": 356
    },
    {
        "type": "mouse",
        "time": 0.8848791122436523,
        "event": "move",
        "x": 668,
        "y": 369
    },
    {
        "type": "mouse",
        "time": 0.8928797245025635,
        "event": "move",
        "x": 690,
        "y": 383
    },
    {
        "type": "mouse",
        "time": 0.9008841514587402,
        "event": "move",
        "x": 713,
        "y": 398
    },
    {
        "type": "mouse",
        "time": 0.9088845252990723,
        "event": "move",
        "x": 736,
        "y": 413
    },
    {
        "type": "mouse",
        "time": 0.9168846607208252,
        "event": "move",
        "x": 760,
        "y": 428
    },
    {
        "type": "mouse",
        "time": 0.924884557723999,
        "event": "move",
        "x": 809,
        "y": 462
    },
    {
        "type": "mouse",
        "time": 0.9328794479370117,
        "event": "move",
        "x": 834,
        "y": 481
    },
    {
        "type": "mouse",
        "time": 0.9408924579620361,
        "event": "move",
        "x": 834,
        "y": 481
    },
    {
        "type": "mouse",
        "time": 0.9488875865936279,
        "event": "move",
        "x": 858,
        "y": 499
    },
    {
        "type": "mouse",
        "time": 0.9563572406768799,
        "event": "move",
        "x": 881,
        "y": 518
    },
    {
        "type": "mouse",
        "time": 0.9643564224243164,
        "event": "move",
        "x": 904,
        "y": 537
    },
    {
        "type": "mouse",
        "time": 0.9723560810089111,
        "event": "move",
        "x": 950,
        "y": 573
    },
    {
        "type": "mouse",
        "time": 0.980355978012085,
        "event": "move",
        "x": 973,
        "y": 591
    },
    {
        "type": "mouse",
        "time": 0.988356351852417,
        "event": "move",
        "x": 995,
        "y": 609
    },
    {
        "type": "mouse",
        "time": 0.996356725692749,
        "event": "move",
        "x": 995,
        "y": 609
    },
    {
        "type": "mouse",
        "time": 1.0043561458587646,
        "event": "move",
        "x": 1039,
        "y": 643
    },
    {
        "type": "mouse",
        "time": 1.0123565196990967,
        "event": "move",
        "x": 1039,
        "y": 643
    },
    {
        "type": "mouse",
        "time": 1.0203564167022705,
        "event": "move",
        "x": 1056,
        "y": 661
    },
    {
        "type": "mouse",
        "time": 1.0283524990081787,
        "event": "move",
        "x": 1071,
        "y": 676
    },
    {
        "type": "mouse",
        "time": 1.0363562107086182,
        "event": "move",
        "x": 1084,
        "y": 689
    },
    {
        "type": "mouse",
        "time": 1.044353723526001,
        "event": "move",
        "x": 1095,
        "y": 702
    },
    {
        "type": "mouse",
        "time": 1.0523574352264404,
        "event": "move",
        "x": 1104,
        "y": 713
    },
    {
        "type": "mouse",
        "time": 1.0603561401367188,
        "event": "move",
        "x": 1111,
        "y": 726
    },
    {
        "type": "mouse",
        "time": 1.0683529376983643,
        "event": "move",
        "x": 1119,
        "y": 736
    },
    {
        "type": "mouse",
        "time": 1.076359510421753,
        "event": "move",
        "x": 1125,
        "y": 747
    },
    {
        "type": "mouse",
        "time": 1.0848753452301025,
        "event": "move",
        "x": 1131,
        "y": 758
    },
    {
        "type": "mouse",
        "time": 1.0923867225646973,
        "event": "move",
        "x": 1138,
        "y": 768
    },
    {
        "type": "mouse",
        "time": 1.1003930568695068,
        "event": "move",
        "x": 1144,
        "y": 777
    },
    {
        "type": "mouse",
        "time": 1.1086373329162598,
        "event": "move",
        "x": 1148,
        "y": 786
    },
    {
        "type": "mouse",
        "time": 1.1166367530822754,
        "event": "move",
        "x": 1151,
        "y": 793
    },
    {
        "type": "mouse",
        "time": 1.1241538524627686,
        "event": "move",
        "x": 1154,
        "y": 801
    },
    {
        "type": "mouse",
        "time": 1.1321539878845215,
        "event": "move",
        "x": 1155,
        "y": 807
    },
    {
        "type": "mouse",
        "time": 1.1401991844177246,
        "event": "move",
        "x": 1156,
        "y": 813
    },
    {
        "type": "mouse",
        "time": 1.1482014656066895,
        "event": "move",
        "x": 1159,
        "y": 824
    },
    {
        "type": "mouse",
        "time": 1.1561994552612305,
        "event": "move",
        "x": 1159,
        "y": 824
    },
    {
        "type": "mouse",
        "time": 1.1641995906829834,
        "event": "move",
        "x": 1160,
        "y": 829
    },
    {
        "type": "mouse",
        "time": 1.1721994876861572,
        "event": "move",
        "x": 1160,
        "y": 833
    },
    {
        "type": "mouse",
        "time": 1.1802012920379639,
        "event": "move",
        "x": 1160,
        "y": 839
    },
    {
        "type": "mouse",
        "time": 1.188201665878296,
        "event": "move",
        "x": 1160,
        "y": 846
    },
    {
        "type": "mouse",
        "time": 1.1967074871063232,
        "event": "move",
        "x": 1160,
        "y": 851
    },
    {
        "type": "mouse",
        "time": 1.2047123908996582,
        "event": "move",
        "x": 1160,
        "y": 857
    },
    {
        "type": "mouse",
        "time": 1.2127130031585693,
        "event": "move",
        "x": 1160,
        "y": 862
    },
    {
        "type": "mouse",
        "time": 1.2207114696502686,
        "event": "move",
        "x": 1160,
        "y": 868
    },
    {
        "type": "mouse",
        "time": 1.2287118434906006,
        "event": "move",
        "x": 1160,
        "y": 874
    },
    {
        "type": "mouse",
        "time": 1.2367112636566162,
        "event": "move",
        "x": 1158,
        "y": 879
    },
    {
        "type": "mouse",
        "time": 1.2447071075439453,
        "event": "move",
        "x": 1156,
        "y": 884
    },
    {
        "type": "mouse",
        "time": 1.2527093887329102,
        "event": "move",
        "x": 1155,
        "y": 889
    },
    {
        "type": "mouse",
        "time": 1.260711669921875,
        "event": "move",
        "x": 1153,
        "y": 894
    },
    {
        "type": "mouse",
        "time": 1.2680964469909668,
        "event": "move",
        "x": 1152,
        "y": 899
    },
    {
        "type": "mouse",
        "time": 1.2761037349700928,
        "event": "move",
        "x": 1152,
        "y": 903
    },
    {
        "type": "mouse",
        "time": 1.284104585647583,
        "event": "move",
        "x": 1152,
        "y": 908
    },
    {
        "type": "mouse",
        "time": 1.292104721069336,
        "event": "move",
        "x": 1152,
        "y": 913
    },
    {
        "type": "mouse",
        "time": 1.3001041412353516,
        "event": "move",
        "x": 1152,
        "y": 917
    },
    {
        "type": "mouse",
        "time": 1.3080999851226807,
        "event": "move",
        "x": 1152,
        "y": 922
    },
    {
        "type": "mouse",
        "time": 1.3161077499389648,
        "event": "move",
        "x": 1152,
        "y": 927
    },
    {
        "type": "mouse",
        "time": 1.324103832244873,
        "event": "move",
        "x": 1152,
        "y": 931
    },
    {
        "type": "mouse",
        "time": 1.3321037292480469,
        "event": "move",
        "x": 1152,
        "y": 934
    },
    {
        "type": "mouse",
        "time": 1.3401446342468262,
        "event": "move",
        "x": 1152,
        "y": 941
    },
    {
        "type": "mouse",
        "time": 1.3481450080871582,
        "event": "move",
        "x": 1152,
        "y": 941
    },
    {
        "type": "mouse",
        "time": 1.3561444282531738,
        "event": "move",
        "x": 1152,
        "y": 948
    },
    {
        "type": "mouse",
        "time": 1.3641443252563477,
        "event": "move",
        "x": 1152,
        "y": 952
    },
    {
        "type": "mouse",
        "time": 1.3731486797332764,
        "event": "move",
        "x": 1152,
        "y": 957
    },
    {
        "type": "mouse",
        "time": 1.3801443576812744,
        "event": "move",
        "x": 1152,
        "y": 957
    },
    {
        "type": "mouse",
        "time": 1.3881449699401855,
        "event": "move",
        "x": 1152,
        "y": 961
    },
    {
        "type": "mouse",
        "time": 1.3961398601531982,
        "event": "move",
        "x": 1152,
        "y": 964
    },
    {
        "type": "mouse",
        "time": 1.404144287109375,
        "event": "move",
        "x": 1152,
        "y": 967
    },
    {
        "type": "mouse",
        "time": 1.4121406078338623,
        "event": "move",
        "x": 1152,
        "y": 973
    },
    {
        "type": "mouse",
        "time": 1.4201445579528809,
        "event": "move",
        "x": 1152,
        "y": 973
    },
    {
        "type": "mouse",
        "time": 1.4291400909423828,
        "event": "move",
        "x": 1150,
        "y": 982
    },
    {
        "type": "mouse",
        "time": 1.4361441135406494,
        "event": "move",
        "x": 1150,
        "y": 982
    },
    {
        "type": "mouse",
        "time": 1.4441442489624023,
        "event": "move",
        "x": 1150,
        "y": 984
    },
    {
        "type": "mouse",
        "time": 1.4521396160125732,
        "event": "move",
        "x": 1150,
        "y": 987
    },
    {
        "type": "mouse",
        "time": 1.460144281387329,
        "event": "move",
        "x": 1150,
        "y": 991
    },
    {
        "type": "mouse",
        "time": 1.4681439399719238,
        "event": "move",
        "x": 1150,
        "y": 994
    },
    {
        "type": "mouse",
        "time": 1.4761443138122559,
        "event": "move",
        "x": 1150,
        "y": 998
    },
    {
        "type": "mouse",
        "time": 1.4841439723968506,
        "event": "move",
        "x": 1150,
        "y": 1007
    },
    {
        "type": "mouse",
        "time": 1.4921441078186035,
        "event": "move",
        "x": 1150,
        "y": 1007
    },
    {
        "type": "mouse",
        "time": 1.5001444816589355,
        "event": "move",
        "x": 1150,
        "y": 1011
    },
    {
        "type": "mouse",
        "time": 1.5081443786621094,
        "event": "move",
        "x": 1150,
        "y": 1014
    },
    {
        "type": "mouse",
        "time": 1.5161395072937012,
        "event": "move",
        "x": 1150,
        "y": 1017
    },
    {
        "type": "mouse",
        "time": 1.524144172668457,
        "event": "move",
        "x": 1150,
        "y": 1019
    },
    {
        "type": "mouse",
        "time": 1.532151460647583,
        "event": "move",
        "x": 1150,
        "y": 1022
    },
    {
        "type": "mouse",
        "time": 1.5401513576507568,
        "event": "move",
        "x": 1150,
        "y": 1023
    },
    {
        "type": "mouse",
        "time": 1.5491943359375,
        "event": "move",
        "x": 1150,
        "y": 1026
    },
    {
        "type": "mouse",
        "time": 1.5561943054199219,
        "event": "move",
        "x": 1150,
        "y": 1028
    },
    {
        "type": "mouse",
        "time": 1.5641956329345703,
        "event": "move",
        "x": 1150,
        "y": 1029
    },
    {
        "type": "mouse",
        "time": 1.5721900463104248,
        "event": "move",
        "x": 1150,
        "y": 1029
    },
    {
        "type": "mouse",
        "time": 1.5801947116851807,
        "event": "move",
        "x": 1150,
        "y": 1031
    },
    {
        "type": "mouse",
        "time": 1.5881941318511963,
        "event": "move",
        "x": 1150,
        "y": 1033
    },
    {
        "type": "mouse",
        "time": 1.5961956977844238,
        "event": "move",
        "x": 1150,
        "y": 1033
    },
    {
        "type": "mouse",
        "time": 1.6041944026947021,
        "event": "move",
        "x": 1150,
        "y": 1036
    },
    {
        "type": "mouse",
        "time": 1.6122915744781494,
        "event": "move",
        "x": 1150,
        "y": 1036
    },
    {
        "type": "mouse",
        "time": 1.636244297027588,
        "event": "move",
        "x": 1150,
        "y": 1037
    },
    {
        "type": "mouse",
        "time": 1.7002863883972168,
        "event": "click",
        "button": "left",
        "pressed": true,
        "x": 1150,
        "y": 1038
    },
    {
        "type": "mouse",
        "time": 1.7812862396240234,
        "event": "click",
        "button": "left",
        "pressed": false,
        "x": 1150,
        "y": 1038
    },
    {
        "type": "mouse",
        "time": 1.8278024196624756,
        "event": "move",
        "x": 1150,
        "y": 1038
    },
    {
        "type": "mouse",
        "time": 1.8363077640533447,
        "event": "move",
        "x": 1150,
        "y": 1038
    },
    {
        "type": "mouse",
        "time": 1.8443126678466797,
        "event": "move",
        "x": 1150,
        "y": 1034
    },
    {
        "type": "mouse",
        "time": 1.852311611175537,
        "event": "move",
        "x": 1150,
        "y": 1029
    },
    {
        "type": "mouse",
        "time": 1.860307216644287,
        "event": "move",
        "x": 1150,
        "y": 1018
    },
    {
        "type": "mouse",
        "time": 1.868307113647461,
        "event": "move",
        "x": 1148,
        "y": 1008
    },
    {
        "type": "mouse",
        "time": 1.8763115406036377,
        "event": "move",
        "x": 1148,
        "y": 1008
    },
    {
        "type": "mouse",
        "time": 1.8853075504302979,
        "event": "move",
        "x": 1147,
        "y": 996
    },
    {
        "type": "mouse",
        "time": 1.8923115730285645,
        "event": "move",
        "x": 1145,
        "y": 984
    },
    {
        "type": "mouse",
        "time": 1.9003117084503174,
        "event": "move",
        "x": 1142,
        "y": 970
    },
    {
        "type": "mouse",
        "time": 1.9083116054534912,
        "event": "move",
        "x": 1140,
        "y": 954
    },
    {
        "type": "mouse",
        "time": 1.9163117408752441,
        "event": "move",
        "x": 1137,
        "y": 936
    },
    {
        "type": "mouse",
        "time": 1.924311637878418,
        "event": "move",
        "x": 1133,
        "y": 919
    },
    {
        "type": "mouse",
        "time": 1.932307243347168,
        "event": "move",
        "x": 1130,
        "y": 900
    },
    {
        "type": "mouse",
        "time": 1.9403159618377686,
        "event": "move",
        "x": 1126,
        "y": 879
    },
    {
        "type": "mouse",
        "time": 1.9483189582824707,
        "event": "move",
        "x": 1123,
        "y": 856
    },
    {
        "type": "mouse",
        "time": 1.9560160636901855,
        "event": "move",
        "x": 1122,
        "y": 834
    },
    {
        "type": "mouse",
        "time": 1.9650094509124756,
        "event": "move",
        "x": 1122,
        "y": 811
    },
    {
        "type": "mouse",
        "time": 1.9730165004730225,
        "event": "move",
        "x": 1122,
        "y": 789
    },
    {
        "type": "mouse",
        "time": 1.9800145626068115,
        "event": "move",
        "x": 1123,
        "y": 764
    },
    {
        "type": "mouse",
        "time": 1.9880881309509277,
        "event": "move",
        "x": 1126,
        "y": 740
    },
    {
        "type": "mouse",
        "time": 1.9960904121398926,
        "event": "move",
        "x": 1131,
        "y": 716
    },
    {
        "type": "mouse",
        "time": 2.0040879249572754,
        "event": "move",
        "x": 1135,
        "y": 691
    },
    {
        "type": "mouse",
        "time": 2.0120880603790283,
        "event": "move",
        "x": 1140,
        "y": 665
    },
    {
        "type": "mouse",
        "time": 2.020087718963623,
        "event": "move",
        "x": 1158,
        "y": 611
    },
    {
        "type": "mouse",
        "time": 2.028087854385376,
        "event": "move",
        "x": 1168,
        "y": 584
    },
    {
        "type": "mouse",
        "time": 2.036083936691284,
        "event": "move",
        "x": 1168,
        "y": 584
    },
    {
        "type": "mouse",
        "time": 2.044084072113037,
        "event": "move",
        "x": 1180,
        "y": 556
    },
    {
        "type": "mouse",
        "time": 2.0520877838134766,
        "event": "move",
        "x": 1213,
        "y": 500
    },
    {
        "type": "mouse",
        "time": 2.060088634490967,
        "event": "move",
        "x": 1231,
        "y": 473
    },
    {
        "type": "mouse",
        "time": 2.068099021911621,
        "event": "move",
        "x": 1231,
        "y": 473
    },
    {
        "type": "mouse",
        "time": 2.077094793319702,
        "event": "move",
        "x": 1271,
        "y": 419
    },
    {
        "type": "mouse",
        "time": 2.0841870307922363,
        "event": "move",
        "x": 1271,
        "y": 419
    },
    {
        "type": "mouse",
        "time": 2.0926971435546875,
        "event": "move",
        "x": 1291,
        "y": 393
    },
    {
        "type": "mouse",
        "time": 2.1007046699523926,
        "event": "move",
        "x": 1311,
        "y": 368
    },
    {
        "type": "mouse",
        "time": 2.1077821254730225,
        "event": "move",
        "x": 1348,
        "y": 326
    },
    {
        "type": "mouse",
        "time": 2.1160457134246826,
        "event": "move",
        "x": 1348,
        "y": 326
    },
    {
        "type": "mouse",
        "time": 2.1240453720092773,
        "event": "move",
        "x": 1365,
        "y": 308
    },
    {
        "type": "mouse",
        "time": 2.1330411434173584,
        "event": "move",
        "x": 1384,
        "y": 291
    },
    {
        "type": "mouse",
        "time": 2.140045642852783,
        "event": "move",
        "x": 1401,
        "y": 276
    },
    {
        "type": "mouse",
        "time": 2.1490461826324463,
        "event": "move",
        "x": 1434,
        "y": 250
    },
    {
        "type": "mouse",
        "time": 2.157041072845459,
        "event": "move",
        "x": 1434,
        "y": 250
    },
    {
        "type": "mouse",
        "time": 2.165040969848633,
        "event": "move",
        "x": 1448,
        "y": 238
    },
    {
        "type": "mouse",
        "time": 2.172046184539795,
        "event": "move",
        "x": 1459,
        "y": 228
    },
    {
        "type": "mouse",
        "time": 2.1800525188446045,
        "event": "move",
        "x": 1470,
        "y": 219
    },
    {
        "type": "mouse",
        "time": 2.1880526542663574,
        "event": "move",
        "x": 1479,
        "y": 210
    },
    {
        "type": "mouse",
        "time": 2.196561813354492,
        "event": "move",
        "x": 1486,
        "y": 201
    },
    {
        "type": "mouse",
        "time": 2.204561233520508,
        "event": "move",
        "x": 1494,
        "y": 194
    },
    {
        "type": "mouse",
        "time": 2.2125611305236816,
        "event": "move",
        "x": 1511,
        "y": 179
    },
    {
        "type": "mouse",
        "time": 2.2205610275268555,
        "event": "move",
        "x": 1511,
        "y": 179
    },
    {
        "type": "mouse",
        "time": 2.2285609245300293,
        "event": "move",
        "x": 1521,
        "y": 170
    },
    {
        "type": "mouse",
        "time": 2.236607313156128,
        "event": "move",
        "x": 1533,
        "y": 163
    },
    {
        "type": "mouse",
        "time": 2.2446072101593018,
        "event": "move",
        "x": 1544,
        "y": 155
    },
    {
        "type": "mouse",
        "time": 2.252607583999634,
        "event": "move",
        "x": 1555,
        "y": 148
    },
    {
        "type": "mouse",
        "time": 2.2606077194213867,
        "event": "move",
        "x": 1564,
        "y": 143
    },
    {
        "type": "mouse",
        "time": 2.2686073780059814,
        "event": "move",
        "x": 1569,
        "y": 140
    },
    {
        "type": "mouse",
        "time": 2.2766079902648926,
        "event": "move",
        "x": 1573,
        "y": 138
    },
    {
        "type": "mouse",
        "time": 2.2846078872680664,
        "event": "move",
        "x": 1574,
        "y": 136
    },
    {
        "type": "mouse",
        "time": 2.2926037311553955,
        "event": "move",
        "x": 1574,
        "y": 136
    },
    {
        "type": "mouse",
        "time": 2.308603286743164,
        "event": "move",
        "x": 1575,
        "y": 135
    },
    {
        "type": "mouse",
        "time": 2.3166069984436035,
        "event": "move",
        "x": 1578,
        "y": 135
    },
    {
        "type": "mouse",
        "time": 2.3326029777526855,
        "event": "move",
        "x": 1578,
        "y": 135
    },
    {
        "type": "mouse",
        "time": 2.340608596801758,
        "event": "move",
        "x": 1579,
        "y": 135
    },
    {
        "type": "mouse",
        "time": 2.3646080493927,
        "event": "move",
        "x": 1581,
        "y": 133
    },
    {
        "type": "mouse",
        "time": 2.388603925704956,
        "event": "move",
        "x": 1581,
        "y": 133
    },
    {
        "type": "mouse",
        "time": 2.3966076374053955,
        "event": "move",
        "x": 1583,
        "y": 133
    },
    {
        "type": "mouse",
        "time": 2.4046075344085693,
        "event": "move",
        "x": 1585,
        "y": 133
    },
    {
        "type": "mouse",
        "time": 2.4126029014587402,
        "event": "move",
        "x": 1591,
        "y": 133
    },
    {
        "type": "mouse",
        "time": 2.420607328414917,
        "event": "move",
        "x": 1591,
        "y": 133
    },
    {
        "type": "mouse",
        "time": 2.4286069869995117,
        "event": "move",
        "x": 1596,
        "y": 133
    },
    {
        "type": "mouse",
        "time": 2.4366023540496826,
        "event": "move",
        "x": 1596,
        "y": 133
    },
    {
        "type": "mouse",
        "time": 2.4446074962615967,
        "event": "move",
        "x": 1600,
        "y": 133
    },
    {
        "type": "mouse",
        "time": 2.4526073932647705,
        "event": "move",
        "x": 1603,
        "y": 133
    },
    {
        "type": "mouse",
        "time": 2.4606025218963623,
        "event": "move",
        "x": 1606,
        "y": 134
    },
    {
        "type": "mouse",
        "time": 2.4686079025268555,
        "event": "move",
        "x": 1610,
        "y": 136
    },
    {
        "type": "mouse",
        "time": 2.476606845855713,
        "event": "move",
        "x": 1610,
        "y": 136
    },
    {
        "type": "mouse",
        "time": 2.484606981277466,
        "event": "move",
        "x": 1614,
        "y": 137
    },
    {
        "type": "mouse",
        "time": 2.4926068782806396,
        "event": "move",
        "x": 1618,
        "y": 138
    },
    {
        "type": "mouse",
        "time": 2.500603199005127,
        "event": "move",
        "x": 1623,
        "y": 139
    },
    {
        "type": "mouse",
        "time": 2.5086071491241455,
        "event": "move",
        "x": 1628,
        "y": 142
    },
    {
        "type": "mouse",
        "time": 2.5166029930114746,
        "event": "move",
        "x": 1633,
        "y": 143
    },
    {
        "type": "mouse",
        "time": 2.5246071815490723,
        "event": "move",
        "x": 1646,
        "y": 148
    },
    {
        "type": "mouse",
        "time": 2.532614231109619,
        "event": "move",
        "x": 1646,
        "y": 148
    },
    {
        "type": "mouse",
        "time": 2.5406148433685303,
        "event": "move",
        "x": 1655,
        "y": 152
    },
    {
        "type": "mouse",
        "time": 2.5489559173583984,
        "event": "move",
        "x": 1663,
        "y": 156
    },
    {
        "type": "mouse",
        "time": 2.5569560527801514,
        "event": "move",
        "x": 1669,
        "y": 159
    },
    {
        "type": "mouse",
        "time": 2.5639543533325195,
        "event": "move",
        "x": 1673,
        "y": 162
    },
    {
        "type": "mouse",
        "time": 2.572950601577759,
        "event": "move",
        "x": 1674,
        "y": 167
    },
    {
        "type": "mouse",
        "time": 2.5809545516967773,
        "event": "move",
        "x": 1672,
        "y": 176
    },
    {
        "type": "mouse",
        "time": 2.588954448699951,
        "event": "move",
        "x": 1672,
        "y": 176
    },
    {
        "type": "mouse",
        "time": 2.6049513816833496,
        "event": "move",
        "x": 1668,
        "y": 177
    },
    {
        "type": "mouse",
        "time": 2.7481069564819336,
        "event": "move",
        "x": 1667,
        "y": 177
    },
    {
        "type": "mouse",
        "time": 2.7561068534851074,
        "event": "move",
        "x": 1660,
        "y": 177
    },
    {
        "type": "mouse",
        "time": 2.7651069164276123,
        "event": "move",
        "x": 1637,
        "y": 176
    },
    {
        "type": "mouse",
        "time": 2.7721760272979736,
        "event": "move",
        "x": 1637,
        "y": 176
    },
    {
        "type": "mouse",
        "time": 2.7801802158355713,
        "event": "move",
        "x": 1627,
        "y": 171
    },
    {
        "type": "mouse",
        "time": 2.7881839275360107,
        "event": "move",
        "x": 1618,
        "y": 165
    },
    {
        "type": "mouse",
        "time": 2.7964344024658203,
        "event": "move",
        "x": 1615,
        "y": 158
    },
    {
        "type": "mouse",
        "time": 2.804438829421997,
        "event": "move",
        "x": 1615,
        "y": 149
    },
    {
        "type": "mouse",
        "time": 2.81243896484375,
        "event": "move",
        "x": 1621,
        "y": 139
    },
    {
        "type": "mouse",
        "time": 2.820434093475342,
        "event": "move",
        "x": 1634,
        "y": 126
    },
    {
        "type": "mouse",
        "time": 2.8284387588500977,
        "event": "move",
        "x": 1666,
        "y": 103
    },
    {
        "type": "mouse",
        "time": 2.8364388942718506,
        "event": "move",
        "x": 1666,
        "y": 103
    },
    {
        "type": "mouse",
        "time": 2.844438314437866,
        "event": "move",
        "x": 1684,
        "y": 91
    },
    {
        "type": "mouse",
        "time": 2.8524386882781982,
        "event": "move",
        "x": 1700,
        "y": 81
    },
    {
        "type": "mouse",
        "time": 2.860438108444214,
        "event": "move",
        "x": 1726,
        "y": 66
    },
    {
        "type": "mouse",
        "time": 2.868438720703125,
        "event": "move",
        "x": 1726,
        "y": 66
    },
    {
        "type": "mouse",
        "time": 2.876433849334717,
        "event": "move",
        "x": 1735,
        "y": 61
    },
    {
        "type": "mouse",
        "time": 2.884434223175049,
        "event": "move",
        "x": 1741,
        "y": 58
    },
    {
        "type": "mouse",
        "time": 2.8924336433410645,
        "event": "move",
        "x": 1745,
        "y": 54
    },
    {
        "type": "mouse",
        "time": 2.9004337787628174,
        "event": "move",
        "x": 1748,
        "y": 51
    },
    {
        "type": "mouse",
        "time": 2.916438579559326,
        "event": "move",
        "x": 1749,
        "y": 49
    },
    {
        "type": "mouse",
        "time": 2.924438953399658,
        "event": "move",
        "x": 1749,
        "y": 48
    },
    {
        "type": "mouse",
        "time": 2.956482172012329,
        "event": "move",
        "x": 1748,
        "y": 45
    },
    {
        "type": "mouse",
        "time": 2.9645330905914307,
        "event": "move",
        "x": 1749,
        "y": 44
    },
    {
        "type": "mouse",
        "time": 2.972536563873291,
        "event": "move",
        "x": 1751,
        "y": 43
    },
    {
        "type": "mouse",
        "time": 2.980536937713623,
        "event": "move",
        "x": 1753,
        "y": 43
    },
    {
        "type": "mouse",
        "time": 2.988537073135376,
        "event": "move",
        "x": 1758,
        "y": 41
    },
    {
        "type": "mouse",
        "time": 2.9965953826904297,
        "event": "move",
        "x": 1758,
        "y": 41
    },
    {
        "type": "mouse",
        "time": 3.0045955181121826,
        "event": "move",
        "x": 1760,
        "y": 40
    },
    {
        "type": "mouse",
        "time": 3.084730863571167,
        "event": "move",
        "x": 1761,
        "y": 38
    },
    {
        "type": "mouse",
        "time": 3.0922422409057617,
        "event": "move",
        "x": 1761,
        "y": 38
    },
    {
        "type": "mouse",
        "time": 3.100248336791992,
        "event": "move",
        "x": 1763,
        "y": 36
    },
    {
        "type": "mouse",
        "time": 3.108246088027954,
        "event": "move",
        "x": 1764,
        "y": 35
    },
    {
        "type": "mouse",
        "time": 3.1165950298309326,
        "event": "move",
        "x": 1765,
        "y": 34
    },
    {
        "type": "mouse",
        "time": 3.1245956420898438,
        "event": "move",
        "x": 1768,
        "y": 33
    },
    {
        "type": "mouse",
        "time": 3.1325910091400146,
        "event": "move",
        "x": 1770,
        "y": 31
    },
    {
        "type": "mouse",
        "time": 3.197112560272217,
        "event": "click",
        "button": "left",
        "pressed": true,
        "x": 1773,
        "y": 30
    },
    {
        "type": "mouse",
        "time": 3.2606723308563232,
        "event": "click",
        "button": "left",
        "pressed": false,
        "x": 1773,
        "y": 30
    },
    {
        "type": "mouse",
        "time": 3.308673143386841,
        "event": "move",
        "x": 1773,
        "y": 30
    },
    {
        "type": "mouse",
        "time": 3.316675901412964,
        "event": "move",
        "x": 1771,
        "y": 30
    },
    {
        "type": "mouse",
        "time": 3.324674129486084,
        "event": "move",
        "x": 1768,
        "y": 30
    },
    {
        "type": "mouse",
        "time": 3.332671642303467,
        "event": "move",
        "x": 1765,
        "y": 30
    },
    {
        "type": "mouse",
        "time": 3.3406684398651123,
        "event": "move",
        "x": 1761,
        "y": 30
    },
    {
        "type": "mouse",
        "time": 3.3486714363098145,
        "event": "move",
        "x": 1755,
        "y": 31
    },
    {
        "type": "mouse",
        "time": 3.3566675186157227,
        "event": "move",
        "x": 1748,
        "y": 32
    },
    {
        "type": "mouse",
        "time": 3.364713191986084,
        "event": "move",
        "x": 1741,
        "y": 33
    },
    {
        "type": "mouse",
        "time": 3.372723340988159,
        "event": "move",
        "x": 1732,
        "y": 36
    },
    {
        "type": "mouse",
        "time": 3.3807222843170166,
        "event": "move",
        "x": 1723,
        "y": 38
    },
    {
        "type": "mouse",
        "time": 3.3887219429016113,
        "event": "move",
        "x": 1712,
        "y": 39
    },
    {
        "type": "mouse",
        "time": 3.396721839904785,
        "event": "move",
        "x": 1698,
        "y": 42
    },
    {
        "type": "mouse",
        "time": 3.404721975326538,
        "event": "move",
        "x": 1682,
        "y": 46
    },
    {
        "type": "mouse",
        "time": 3.4127230644226074,
        "event": "move",
        "x": 1665,
        "y": 49
    },
    {
        "type": "mouse",
        "time": 3.4207229614257812,
        "event": "move",
        "x": 1645,
        "y": 56
    },
    {
        "type": "mouse",
        "time": 3.428717613220215,
        "event": "move",
        "x": 1623,
        "y": 63
    },
    {
        "type": "mouse",
        "time": 3.4367196559906006,
        "event": "move",
        "x": 1600,
        "y": 69
    },
    {
        "type": "mouse",
        "time": 3.4447219371795654,
        "event": "move",
        "x": 1573,
        "y": 77
    },
    {
        "type": "mouse",
        "time": 3.4527218341827393,
        "event": "move",
        "x": 1546,
        "y": 84
    },
    {
        "type": "mouse",
        "time": 3.4607176780700684,
        "event": "move",
        "x": 1516,
        "y": 93
    },
    {
        "type": "mouse",
        "time": 3.468722105026245,
        "event": "move",
        "x": 1445,
        "y": 114
    },
    {
        "type": "mouse",
        "time": 3.476722240447998,
        "event": "move",
        "x": 1445,
        "y": 114
    },
    {
        "type": "mouse",
        "time": 3.484722375869751,
        "event": "move",
        "x": 1406,
        "y": 126
    },
    {
        "type": "mouse",
        "time": 3.4927220344543457,
        "event": "move",
        "x": 1322,
        "y": 148
    },
    {
        "type": "mouse",
        "time": 3.5007219314575195,
        "event": "move",
        "x": 1281,
        "y": 159
    },
    {
        "type": "mouse",
        "time": 3.5087220668792725,
        "event": "move",
        "x": 1281,
        "y": 159
    },
    {
        "type": "mouse",
        "time": 3.5167226791381836,
        "event": "move",
        "x": 1240,
        "y": 169
    },
    {
        "type": "mouse",
        "time": 3.5247230529785156,
        "event": "move",
        "x": 1196,
        "y": 179
    },
    {
        "type": "mouse",
        "time": 3.5327296257019043,
        "event": "move",
        "x": 1152,
        "y": 188
    },
    {
        "type": "mouse",
        "time": 3.5407285690307617,
        "event": "move",
        "x": 1065,
        "y": 206
    },
    {
        "type": "mouse",
        "time": 3.5482447147369385,
        "event": "move",
        "x": 1065,
        "y": 206
    },
    {
        "type": "mouse",
        "time": 3.5562455654144287,
        "event": "move",
        "x": 1023,
        "y": 213
    },
    {
        "type": "mouse",
        "time": 3.5642452239990234,
        "event": "move",
        "x": 983,
        "y": 221
    },
    {
        "type": "mouse",
        "time": 3.5722451210021973,
        "event": "move",
        "x": 945,
        "y": 229
    },
    {
        "type": "mouse",
        "time": 3.580240249633789,
        "event": "move",
        "x": 908,
        "y": 237
    },
    {
        "type": "mouse",
        "time": 3.588244676589966,
        "event": "move",
        "x": 875,
        "y": 243
    },
    {
        "type": "mouse",
        "time": 3.596245288848877,
        "event": "move",
        "x": 845,
        "y": 249
    },
    {
        "type": "mouse",
        "time": 3.604246139526367,
        "event": "move",
        "x": 817,
        "y": 254
    },
    {
        "type": "mouse",
        "time": 3.6122446060180664,
        "event": "move",
        "x": 791,
        "y": 262
    },
    {
        "type": "mouse",
        "time": 3.6202423572540283,
        "event": "move",
        "x": 768,
        "y": 269
    },
    {
        "type": "mouse",
        "time": 3.628244638442993,
        "event": "move",
        "x": 746,
        "y": 276
    },
    {
        "type": "mouse",
        "time": 3.6362404823303223,
        "event": "move",
        "x": 723,
        "y": 283
    },
    {
        "type": "mouse",
        "time": 3.64424467086792,
        "event": "move",
        "x": 703,
        "y": 291
    },
    {
        "type": "mouse",
        "time": 3.652244806289673,
        "event": "move",
        "x": 685,
        "y": 297
    },
    {
        "type": "mouse",
        "time": 3.6602535247802734,
        "event": "move",
        "x": 666,
        "y": 303
    },
    {
        "type": "mouse",
        "time": 3.668248414993286,
        "event": "move",
        "x": 650,
        "y": 308
    },
    {
        "type": "mouse",
        "time": 3.6767666339874268,
        "event": "move",
        "x": 632,
        "y": 312
    },
    {
        "type": "mouse",
        "time": 3.6840896606445312,
        "event": "move",
        "x": 615,
        "y": 316
    },
    {
        "type": "mouse",
        "time": 3.692089319229126,
        "event": "move",
        "x": 598,
        "y": 318
    },
    {
        "type": "mouse",
        "time": 3.700089454650879,
        "event": "move",
        "x": 582,
        "y": 322
    },
    {
        "type": "mouse",
        "time": 3.708090305328369,
        "event": "move",
        "x": 567,
        "y": 324
    },
    {
        "type": "mouse",
        "time": 3.7160894870758057,
        "event": "move",
        "x": 555,
        "y": 327
    },
    {
        "type": "mouse",
        "time": 3.7240891456604004,
        "event": "move",
        "x": 542,
        "y": 329
    },
    {
        "type": "mouse",
        "time": 3.7320899963378906,
        "event": "move",
        "x": 531,
        "y": 332
    },
    {
        "type": "mouse",
        "time": 3.7410895824432373,
        "event": "move",
        "x": 521,
        "y": 333
    },
    {
        "type": "mouse",
        "time": 3.7480897903442383,
        "event": "move",
        "x": 512,
        "y": 334
    },
    {
        "type": "mouse",
        "time": 3.756089448928833,
        "event": "move",
        "x": 500,
        "y": 334
    },
    {
        "type": "mouse",
        "time": 3.765085220336914,
        "event": "move",
        "x": 495,
        "y": 334
    },
    {
        "type": "mouse",
        "time": 3.772090435028076,
        "event": "move",
        "x": 495,
        "y": 334
    },
    {
        "type": "mouse",
        "time": 3.78008770942688,
        "event": "move",
        "x": 490,
        "y": 334
    },
    {
        "type": "mouse",
        "time": 3.788092851638794,
        "event": "move",
        "x": 487,
        "y": 334
    },
    {
        "type": "mouse",
        "time": 3.79660964012146,
        "event": "move",
        "x": 485,
        "y": 334
    },
    {
        "type": "mouse",
        "time": 3.8046059608459473,
        "event": "move",
        "x": 482,
        "y": 334
    },
    {
        "type": "mouse",
        "time": 3.884125232696533,
        "event": "move",
        "x": 481,
        "y": 334
    },
    {
        "type": "mouse",
        "time": 3.892127752304077,
        "event": "move",
        "x": 480,
        "y": 334
    },
    {
        "type": "mouse",
        "time": 3.90012788772583,
        "event": "move",
        "x": 477,
        "y": 334
    },
    {
        "type": "mouse",
        "time": 3.9081239700317383,
        "event": "move",
        "x": 475,
        "y": 334
    },
    {
        "type": "mouse",
        "time": 3.916127920150757,
        "event": "move",
        "x": 471,
        "y": 334
    },
    {
        "type": "mouse",
        "time": 3.924128293991089,
        "event": "move",
        "x": 468,
        "y": 333
    },
    {
        "type": "mouse",
        "time": 3.93212890625,
        "event": "move",
        "x": 467,
        "y": 331
    },
    {
        "type": "mouse",
        "time": 3.9401278495788574,
        "event": "move",
        "x": 466,
        "y": 330
    },
    {
        "type": "mouse",
        "time": 3.9562935829162598,
        "event": "move",
        "x": 465,
        "y": 329
    },
    {
        "type": "mouse",
        "time": 3.9642934799194336,
        "event": "move",
        "x": 461,
        "y": 328
    },
    {
        "type": "mouse",
        "time": 3.980384349822998,
        "event": "move",
        "x": 461,
        "y": 328
    },
    {
        "type": "mouse",
        "time": 3.9963834285736084,
        "event": "move",
        "x": 460,
        "y": 325
    },
    {
        "type": "mouse",
        "time": 4.004383087158203,
        "event": "move",
        "x": 458,
        "y": 323
    },
    {
        "type": "mouse",
        "time": 4.012383937835693,
        "event": "move",
        "x": 457,
        "y": 321
    },
    {
        "type": "mouse",
        "time": 4.02038311958313,
        "event": "move",
        "x": 456,
        "y": 320
    },
    {
        "type": "mouse",
        "time": 4.028383255004883,
        "event": "move",
        "x": 455,
        "y": 319
    },
    {
        "type": "mouse",
        "time": 4.036383152008057,
        "event": "move",
        "x": 453,
        "y": 318
    },
    {
        "type": "mouse",
        "time": 4.0443830490112305,
        "event": "move",
        "x": 450,
        "y": 314
    },
    {
        "type": "mouse",
        "time": 4.052382946014404,
        "event": "move",
        "x": 450,
        "y": 314
    },
    {
        "type": "mouse",
        "time": 4.060383558273315,
        "event": "move",
        "x": 448,
        "y": 313
    },
    {
        "type": "mouse",
        "time": 4.068390130996704,
        "event": "move",
        "x": 446,
        "y": 309
    },
    {
        "type": "mouse",
        "time": 4.076390266418457,
        "event": "move",
        "x": 446,
        "y": 309
    },
    {
        "type": "mouse",
        "time": 4.084921598434448,
        "event": "move",
        "x": 442,
        "y": 306
    },
    {
        "type": "mouse",
        "time": 4.092973470687866,
        "event": "move",
        "x": 442,
        "y": 306
    },
    {
        "type": "mouse",
        "time": 4.100976467132568,
        "event": "move",
        "x": 441,
        "y": 305
    },
    {
        "type": "mouse",
        "time": 4.108978986740112,
        "event": "move",
        "x": 440,
        "y": 304
    },
    {
        "type": "mouse",
        "time": 4.116344690322876,
        "event": "move",
        "x": 438,
        "y": 303
    },
    {
        "type": "mouse",
        "time": 4.124344348907471,
        "event": "move",
        "x": 436,
        "y": 301
    },
    {
        "type": "mouse",
        "time": 4.132344484329224,
        "event": "move",
        "x": 435,
        "y": 300
    },
    {
        "type": "mouse",
        "time": 4.1403443813323975,
        "event": "move",
        "x": 432,
        "y": 299
    },
    {
        "type": "mouse",
        "time": 4.148340225219727,
        "event": "move",
        "x": 431,
        "y": 296
    },
    {
        "type": "mouse",
        "time": 4.156344413757324,
        "event": "move",
        "x": 430,
        "y": 295
    },
    {
        "type": "mouse",
        "time": 4.164344549179077,
        "event": "move",
        "x": 428,
        "y": 294
    },
    {
        "type": "mouse",
        "time": 4.172344446182251,
        "event": "move",
        "x": 426,
        "y": 293
    },
    {
        "type": "mouse",
        "time": 4.180347204208374,
        "event": "move",
        "x": 425,
        "y": 291
    },
    {
        "type": "mouse",
        "time": 4.188467979431152,
        "event": "move",
        "x": 423,
        "y": 290
    },
    {
        "type": "mouse",
        "time": 4.196978330612183,
        "event": "move",
        "x": 421,
        "y": 289
    },
    {
        "type": "mouse",
        "time": 4.204977750778198,
        "event": "move",
        "x": 420,
        "y": 288
    },
    {
        "type": "mouse",
        "time": 4.212977647781372,
        "event": "move",
        "x": 418,
        "y": 286
    },
    {
        "type": "mouse",
        "time": 4.220982551574707,
        "event": "move",
        "x": 417,
        "y": 284
    },
    {
        "type": "mouse",
        "time": 4.228982448577881,
        "event": "move",
        "x": 415,
        "y": 281
    },
    {
        "type": "mouse",
        "time": 4.236982107162476,
        "event": "move",
        "x": 412,
        "y": 280
    },
    {
        "type": "mouse",
        "time": 4.244982957839966,
        "event": "move",
        "x": 410,
        "y": 278
    },
    {
        "type": "mouse",
        "time": 4.252982139587402,
        "event": "move",
        "x": 407,
        "y": 274
    },
    {
        "type": "mouse",
        "time": 4.260982036590576,
        "event": "move",
        "x": 405,
        "y": 270
    },
    {
        "type": "mouse",
        "time": 4.2689783573150635,
        "event": "move",
        "x": 403,
        "y": 266
    },
    {
        "type": "mouse",
        "time": 4.276982307434082,
        "event": "move",
        "x": 401,
        "y": 264
    },
    {
        "type": "mouse",
        "time": 4.284978628158569,
        "event": "move",
        "x": 398,
        "y": 263
    },
    {
        "type": "mouse",
        "time": 4.292982339859009,
        "event": "move",
        "x": 395,
        "y": 259
    },
    {
        "type": "mouse",
        "time": 4.299982309341431,
        "event": "move",
        "x": 395,
        "y": 259
    },
    {
        "type": "mouse",
        "time": 4.308978319168091,
        "event": "move",
        "x": 393,
        "y": 256
    },
    {
        "type": "mouse",
        "time": 4.316978693008423,
        "event": "move",
        "x": 392,
        "y": 255
    },
    {
        "type": "mouse",
        "time": 4.324981927871704,
        "event": "move",
        "x": 391,
        "y": 253
    },
    {
        "type": "mouse",
        "time": 4.331982135772705,
        "event": "move",
        "x": 387,
        "y": 249
    },
    {
        "type": "mouse",
        "time": 4.3409788608551025,
        "event": "move",
        "x": 386,
        "y": 246
    },
    {
        "type": "mouse",
        "time": 4.347982168197632,
        "event": "move",
        "x": 386,
        "y": 246
    },
    {
        "type": "mouse",
        "time": 4.3649821281433105,
        "event": "move",
        "x": 385,
        "y": 244
    },
    {
        "type": "mouse",
        "time": 4.372978925704956,
        "event": "move",
        "x": 383,
        "y": 240
    },
    {
        "type": "mouse",
        "time": 4.379981994628906,
        "event": "move",
        "x": 382,
        "y": 239
    },
    {
        "type": "mouse",
        "time": 4.387977600097656,
        "event": "move",
        "x": 381,
        "y": 238
    },
    {
        "type": "mouse",
        "time": 4.404982328414917,
        "event": "move",
        "x": 380,
        "y": 236
    },
    {
        "type": "mouse",
        "time": 4.411981821060181,
        "event": "move",
        "x": 380,
        "y": 235
    },
    {
        "type": "mouse",
        "time": 4.428977012634277,
        "event": "move",
        "x": 378,
        "y": 233
    },
    {
        "type": "mouse",
        "time": 4.436977386474609,
        "event": "move",
        "x": 378,
        "y": 231
    },
    {
        "type": "mouse",
        "time": 4.444977760314941,
        "event": "move",
        "x": 377,
        "y": 229
    },
    {
        "type": "mouse",
        "time": 4.451982259750366,
        "event": "move",
        "x": 376,
        "y": 228
    },
    {
        "type": "mouse",
        "time": 4.459981918334961,
        "event": "move",
        "x": 375,
        "y": 226
    },
    {
        "type": "mouse",
        "time": 4.524977445602417,
        "event": "click",
        "button": "left",
        "pressed": true,
        "x": 373,
        "y": 225
    }
]